MANIFEST.in
README.md
setup.py
hiscore/__init__.py
hiscore/engine.py
hiscore/errors.py
hiscore.egg-info/PKG-INFO
hiscore.egg-info/SOURCES.txt
hiscore.egg-info/dependency_links.txt
hiscore.egg-info/requires.txt
hiscore.egg-info/top_level.txt