Metadata-Version: 1.1
Name: hiscore
Version: 1.1.0
Summary: A simple and powerful engine for creating scores
Home-page: https://github.com/aothman/hiscore
Author: Abraham Othman
Author-email: aothman@cs.cmu.edu
License: UNKNOWN
Platform: UNKNOWN
Classifier: Development Status :: 5 - Production/Stable
Classifier: Intended Audience :: Science/Research
Classifier: License :: OSI Approved :: GNU Affero General Public License v3
Classifier: Programming Language :: Python :: 2
